bionicblue/__init__.py
bionicblue/__main__.py
bionicblue/appinfo.py
bionicblue/config.py
bionicblue/constants.py
bionicblue/ensurepygamece.py
bionicblue/exceptions.py
bionicblue/palette.py
bionicblue/surfsman.py
bionicblue/textman.py
bionicblue/ani2d/__init__.py
bionicblue/ani2d/player.py
bionicblue/ani2d/processing/__init__.py
bionicblue/ani2d/processing/constants.py
bionicblue/ani2d/processing/derived.py
bionicblue/ani2d/processing/recolor.py
bionicblue/classes2d/__init__.py
bionicblue/classes2d/collections.py
bionicblue/classes2d/single.py
bionicblue/classes2d/surfaceswitcher.py
bionicblue/data/game_icon.png
bionicblue/data/animations/blue_shooter_man/instructions.pyl
bionicblue/data/animations/blue_shooter_man/shooter_man.pxa
bionicblue/data/animations/death_rings/death_ring00_expanding.pos
bionicblue/data/animations/death_rings/death_ring01_expanding.pos
bionicblue/data/animations/death_rings/death_ring02_expanding.pos
bionicblue/data/animations/death_rings/death_ring03_expanding.pos
bionicblue/data/animations/death_rings/death_ring04_expanding.pos
bionicblue/data/animations/death_rings/death_ring05_expanding.pos
bionicblue/data/animations/death_rings/death_rings.pxa
bionicblue/data/animations/death_rings/instructions.pyl
bionicblue/data/animations/explosion/explosions.pxa
bionicblue/data/animations/explosion/instructions.pyl
bionicblue/data/animations/full_charged_shot/full_charged_shot.pxa
bionicblue/data/animations/full_charged_shot/instructions.pyl
bionicblue/data/animations/grunt_bot/grunt_bot.pxa
bionicblue/data/animations/grunt_bot/instructions.pyl
bionicblue/data/animations/middle_charged_shot/instructions.pyl
bionicblue/data/animations/middle_charged_shot/middle_charged_shot.pxa
bionicblue/data/fonts/ark_pixel_12px_latin.ttf
bionicblue/data/images/alpha/blue_shooter_man_head.png
bionicblue/data/images/alpha/ladder.png
bionicblue/data/images/no_alpha/city_block.png
bionicblue/data/images/no_alpha/city_wall.png
bionicblue-0.12.2.dist-info/METADATA
bionicblue-0.12.2.dist-info/WHEEL
bionicblue-0.12.2.dist-info/entry_points.txt
bionicblue-0.12.2.dist-info/top_level.txt
bionicblue-0.12.2.dist-info/RECORD
