Metadata-Version: 2.4
Name: bionicblue
Version: 0.12.2
Summary: A bionic boy fights robots to protect humanity in this action platformer game
Author-email: Kennedy Richard <kennedy@kennedyrichard.com>
License: Unlicense
Project-URL: Homepage, https://bionicblue.indiesmiths.com
Project-URL: Source Code, https://github.com/IndieSmiths/bionicblue
Project-URL: Forum, https://github.com/IndieSmiths/bionicblue/discussions
Project-URL: Bug Tracker, https://github.com/IndieSmiths/bionicblue/issues
Project-URL: Donate, https://indiesmiths.com/donate
Keywords: gui,desktop,application,pygame,pygame-ce,game,indie,video game
Classifier: License :: OSI Approved :: The Unlicense (Unlicense)
Classifier: Development Status :: 4 - Beta
Classifier: Programming Language :: Python :: 3
Classifier: Programming Language :: Python :: Implementation :: CPython
Classifier: Topic :: Games/Entertainment
Classifier: Topic :: Games/Entertainment :: Side-Scrolling/Arcade Games
Classifier: Topic :: Software Development
Classifier: Topic :: Software Development :: Libraries :: pygame
Classifier: Topic :: Desktop Environment
Classifier: Topic :: Multimedia
Classifier: Intended Audience :: End Users/Desktop
Requires-Python: >=3.7
Requires-Dist: pygame-ce
